ansiformatter/__init__.cpython-312.so
ansiformatter/constants.cpython-312.so
ansiformatter/formatter.cpython-312.so
ansiformatter/utils.cpython-312.so
ansiformatter-0.1.0.dist-info/METADATA
ansiformatter-0.1.0.dist-info/WHEEL
ansiformatter-0.1.0.dist-info/top_level.txt
ansiformatter-0.1.0.dist-info/RECORD
