Metadata-Version: 2.4
Name: ansiformatter
Version: 0.1.0
Summary: A package for formatting text in terminal using ANSI in Python
Home-page: https://github.com/quillaiMohammed/ansi-formatter
Author: Quillai Mohammed Eisa
Author-email: quillai20011114@gmail.com
Requires-Python: >=3.9
Dynamic: author
Dynamic: author-email
Dynamic: description
Dynamic: description-content-type
Dynamic: home-page
Dynamic: requires-python
Dynamic: summary
